httpshare/LICENSE.txt
httpshare/__init__.py
httpshare/_index.stpl
httpshare/_upload_form.stpl
httpshare/app.py
httpshare/base.stpl
httpshare/home_index.stpl
httpshare/license_page.stpl
httpshare/main.py
httpshare/normal_index.stpl
httpshare/version.py
httpshare-1.0.6.dist-info/LICENSE.txt
httpshare-1.0.6.dist-info/METADATA
httpshare-1.0.6.dist-info/WHEEL
httpshare-1.0.6.dist-info/entry_points.txt
httpshare-1.0.6.dist-info/top_level.txt
httpshare-1.0.6.dist-info/zip-safe
httpshare-1.0.6.dist-info/RECORD
