Metadata-Version: 2.1
Name: httpshare
Version: 1.0.6
Summary: Q&D file transfer utility using an ephemeral HTTP service
Home-page: https://github.com/lourkeur/httpshare-pypi
Author: Louis Bettens
Author-email: louis@bettens.info
License: zlib
Keywords: filetransfer
Platform: UNKNOWN
Classifier: Environment :: Console
Classifier: Intended Audience :: End Users/Desktop
Classifier: Topic :: Software Development :: Build Tools
Classifier: License :: OSI Approved :: zlib/libpng License
Classifier: Programming Language :: Python :: 2.7
Classifier: Programming Language :: Python :: 3.4
Classifier: Programming Language :: Python :: 3.5
Classifier: Programming Language :: Python :: 3.6
Classifier: Topic :: Communications :: File Sharing
Classifier: Topic :: Utilities
Requires-Dist: bottle (==0.12.16)
Requires-Dist: colorama (==0.4.1)
Requires-Dist: docopt (==0.6.2)
Requires-Dist: qrcode (==6.0)
